{
  "schema_version": 1,
  "kind": "work",
  "eul_wid": "hps-au",
  "eul_aid": "hps",
  "author_slug": "menander-of-athens",
  "work_slug": "uncertain-fable",
  "url_slug": "menander-of-athens-uncertain-fable-hps-au",
  "author": {
    "english": "Menander of Athens",
    "ancient_greek": "Μένανδρος ὁ Ἀθηναῖος"
  },
  "title": {
    "english": "Uncertain Fable",
    "ancient_greek": "Ἄδηλος Μῦθος"
  },
  "seo": {
    "browser_title": "Uncertain Fable by Menander of Athens on Eulogikon",
    "meta_title": "Classical Uncertain Fable by Menander in Ancient Greek Text",
    "meta_description": "The Uncertain Fable is a lost comedy exploring mistaken identity and social relationships. Read free and download in original ancient Greek at Eulogikon."
  },
  "metadata": [
    {
      "label": "Period",
      "greek": "Ἑλληνιστική",
      "english": "Hellenistic",
      "href": "/periods/hellenistic"
    },
    {
      "label": "Dialect",
      "greek": "Κωμῳδία Ἀττική",
      "english": "Attic Comedy",
      "href": "/dialects/att"
    },
    {
      "label": "Domain",
      "greek": "Κωμῳδία",
      "english": "Comedy",
      "href": "/domains/comedy"
    },
    {
      "label": "Format",
      "greek": "Ἔμμετρος",
      "english": "Verse",
      "href": null
    }
  ],
  "research_html": "<div class=\"research-section\">\n<p class=\"research-text\">The <strong>Uncertain Fable</strong> is a lost comedy by the Athenian playwright Menander, composed in verse in the late fourth or early third century BCE. As a work of New Comedy, it represents a shift from the political satire of earlier Athenian drama toward plots centered on domestic and romantic entanglements. The play survives only in fragments, totaling eighty-seven brief passages. These were preserved primarily through quotation by later authors who valued their stylistic or moral content, with a small additional number recovered from papyrus discoveries. The title implies a narrative constructed around misunderstanding or concealed truth. Modern scholarship, drawing on the extant fragments and the conventions of Menander&#x27;s other works, suggests the plot likely involved elements of mistaken identity, familial secrets, and a climactic revelation, reflecting the playwright&#x27;s enduring thematic focus on chance, human character, and social dynamics.</p>\n</div>",
  "rows": [
    {
      "kind": "text",
      "reference": "3.1",
      "text": "ἐπ[",
      "witness_prefix": "",
      "speaker": null
    },
    {
      "kind": "text",
      "reference": "3.2",
      "text": "ἔχ[",
      "witness_prefix": "",
      "speaker": null
    },
    {
      "kind": "text",
      "reference": "4",
      "text": "‵—′",
      "witness_prefix": "",
      "speaker": null
    },
    {
      "kind": "text",
      "reference": "5",
      "text": "ἐκσωσ[",
      "witness_prefix": "",
      "speaker": null
    },
    {
      "kind": "text",
      "reference": "5.1",
      "text": "‵—′",
      "witness_prefix": "",
      "speaker": null
    },
    {
      "kind": "text",
      "reference": "5.2",
      "text": "μάρτυρα[",
      "witness_prefix": "",
      "speaker": null
    },
    {
      "kind": "text",
      "reference": "5.3",
      "text": "ἐπ’ ἄλλα ς.[",
      "witness_prefix": "",
      "speaker": null
    },
    {
      "kind": "text",
      "reference": "5.4",
      "text": "γείτοσιν ἑτοιμ[",
      "witness_prefix": "",
      "speaker": null
    },
    {
      "kind": "text",
      "reference": "5.5",
      "text": "τὸν ἐγκεκλει[",
      "witness_prefix": "",
      "speaker": null
    },
    {
      "kind": "text",
      "reference": "10",
      "text": "(ΛΑΧΗΣ)",
      "witness_prefix": "",
      "speaker": null
    },
    {
      "kind": "text",
      "reference": "10.1",
      "text": "παῖ, Μοσχίων [",
      "witness_prefix": "",
      "speaker": null
    },
    {
      "kind": "text",
      "reference": "10.2",
      "text": "Ἀρεοπαγίτης ε[",
      "witness_prefix": "",
      "speaker": null
    },
    {
      "kind": "text",
      "reference": "11.1",
      "text": "‵—′",
      "witness_prefix": "",
      "speaker": null
    },
    {
      "kind": "text",
      "reference": "11.2",
      "text": "ἔτι γάρ [ς’ ἑ]τ[α]ῖρ[ον",
      "witness_prefix": "",
      "speaker": null
    },
    {
      "kind": "text",
      "reference": "11.3",
      "text": "(ΧΑΙΡΕΑΣ)",
      "witness_prefix": "",
      "speaker": null
    },
    {
      "kind": "text",
      "reference": "13.1",
      "text": "ἀδικεῖ μ’ ἐκεῖνος οὐδὲν ἐξ ἐμοῦ παθών.",
      "witness_prefix": "",
      "speaker": null
    },
    {
      "kind": "text",
      "reference": "13.2",
      "text": "ἤρα μὲν ἀεὶ τῆς κόρης καὶ πολλά μοι",
      "witness_prefix": "",
      "speaker": null
    },
    {
      "kind": "text",
      "reference": "15.1",
      "text": "πράγματα παρεῖχεν, ὡς δ’ ἐπέραινεν οὐδὲ ἓν",
      "witness_prefix": "",
      "speaker": null
    },
    {
      "kind": "text",
      "reference": "15.2",
      "text": "αὑτῶι παραδοῦναι τὸν [γάμο]ν πείθων, ἰδού,",
      "witness_prefix": "",
      "speaker": null
    },
    {
      "kind": "text",
      "reference": "15.3",
      "text": "ἐξειργάσατο.",
      "witness_prefix": "",
      "speaker": null
    },
    {
      "kind": "text",
      "reference": "17.1",
      "text": "(Λα) τί οὖν; ἀναίνει τὴν ἐμὴν",
      "witness_prefix": "",
      "speaker": null
    },
    {
      "kind": "text",
      "reference": "17.2",
      "text": "ἔχειν θυγατέρα;",
      "witness_prefix": "",
      "speaker": null
    },
    {
      "kind": "text",
      "reference": "18.1",
      "text": "(Χαι) τοῖς δὲ δοῦσι τίνα λόγον",
      "witness_prefix": "",
      "speaker": null
    },
    {
      "kind": "text",
      "reference": "18.2",
      "text": "ἐρῶ, Λάχης;",
      "witness_prefix": "",
      "speaker": null
    },
    {
      "kind": "text",
      "reference": "19",
      "text": "(Λα) γενοῦ γάρ, ἱκετεύω [ς’] ἐγώ—",
      "witness_prefix": "",
      "speaker": null
    },
    {
      "kind": "text",
      "reference": "20",
      "text": "(Χαι) οἴμοι, τί ποήσω;",
      "witness_prefix": "",
      "speaker": null
    },
    {
      "kind": "text",
      "reference": "20.1",
      "text": "(ΚΛΕΑΙΝΕΤΟΣ) τίς ὁ βοῶν ἐστίν ποτε",
      "witness_prefix": "",
      "speaker": null
    },
    {
      "kind": "text",
      "reference": "20.2",
      "text": "πρὸς ταῖς θύραις;",
      "witness_prefix": "",
      "speaker": null
    },
    {
      "kind": "text",
      "reference": "21.1",
      "text": "(?Χαι) εὐκαιρότ[α〈τά〉 γ]ε νὴ Δία",
      "witness_prefix": "",
      "speaker": null
    },
    {
      "kind": "text",
      "reference": "21.2",
      "text": "[ ]εμε. τί ποήσω, Λάχης;",
      "witness_prefix": "",
      "speaker": null
    },
    {
      "kind": "text",
      "reference": "21.3",
      "text": "(Λα) πείθωμεν αὐτόν.",
      "witness_prefix": "",
      "speaker": null
    },
    {
      "kind": "text",
      "reference": "23.1",
      "text": "(Χαι) ὢ βίας ἐρρωμένης.",
      "witness_prefix": "",
      "speaker": null
    },
    {
      "kind": "text",
      "reference": "23.2",
      "text": "πείθω παραδοῦναι τὴν ἐμὴν ἀδικούμενος",
      "witness_prefix": "",
      "speaker": null
    },
    {
      "kind": "text",
      "reference": "25",
      "text": "αὐτός;",
      "witness_prefix": "",
      "speaker": null
    },
    {
      "kind": "text",
      "reference": "25",
      "text": "(Λα) ὑπόμεινον δι’ ἐμέ.",
      "witness_prefix": "",
      "speaker": null
    },
    {
      "kind": "text",
      "reference": "25.1",
      "text": "(Χαι) νὴ τὸν Ἥλιον",
      "witness_prefix": "",
      "speaker": null
    },
    {
      "kind": "text",
      "reference": "25.2",
      "text": "αἰσχύνομαι Λάχης σε. τί.....[",
      "witness_prefix": "",
      "speaker": null
    },
    {
      "kind": "text",
      "reference": "25.3",
      "text": "ἄκουε δή μου. Μοσχίων τὴν παρθένον",
      "witness_prefix": "",
      "speaker": null
    },
    {
      "kind": "text",
      "reference": "25.4",
      "text": "ἑλ]ὼν ἔχει, Κλεαίνετε.",
      "witness_prefix": "",
      "speaker": null
    },
    {
      "kind": "text",
      "reference": "28.1",
      "text": "〈Κλ〉 ἠδικήμεθα.",
      "witness_prefix": "",
      "speaker": null
    },
    {
      "kind": "text",
      "reference": "28.2",
      "text": "(Χαι) μηθὲν βοήσηις. γνησίων ἐπὶ σπορᾶι",
      "witness_prefix": "",
      "speaker": null
    },
    {
      "kind": "text",
      "reference": "30.1",
      "text": "παίδων. ὁ πατὴρ αὐτοῦ [παρ]ὼν Λάχης ὁδὶ",
      "witness_prefix": "",
      "speaker": null
    },
    {
      "kind": "text",
      "reference": "30.2",
      "text": "τοῦτ’ ἐπιβεβαιοῖ. φὴις σ[ύ;",
      "witness_prefix": "",
      "speaker": null
    },
    {
      "kind": "text",
      "reference": "31.1",
      "text": "[Λα] φημ]ί, Χαιρέα.",
      "witness_prefix": "",
      "speaker": null
    },
    {
      "kind": "text",
      "reference": "31.2",
      "text": "οὐ] γάρ τι βούλ[",
      "witness_prefix": "",
      "speaker": null
    },
    {
      "kind": "text",
      "reference": "31.3",
      "text": "(desunt uersus v uel vi)",
      "witness_prefix": "",
      "speaker": null
    },
    {
      "kind": "text",
      "reference": "31.4",
      "text": "]πος ἦν",
      "witness_prefix": "",
      "speaker": null
    },
    {
      "kind": "text",
      "reference": "35.1",
      "text": "] ἐμοὶ",
      "witness_prefix": "",
      "speaker": null
    },
    {
      "kind": "text",
      "reference": "35.2",
      "text": "κα]λῶς ἔχει:",
      "witness_prefix": "",
      "speaker": null
    },
    {
      "kind": "text",
      "reference": "35.3",
      "text": "κα]τὰ τρόπον",
      "witness_prefix": "",
      "speaker": null
    },
    {
      "kind": "text",
      "reference": "35.4",
      "text": "]γάρ μοι διαφέρει",
      "witness_prefix": "",
      "speaker": null
    },
    {
      "kind": "text",
      "reference": "35.5",
      "text": "τ]ὰ γεγονότα:",
      "witness_prefix": "",
      "speaker": null
    },
    {
      "kind": "text",
      "reference": "40.1",
      "text": "]πρᾶός γ’ εἶ σφόδρα",
      "witness_prefix": "",
      "speaker": null
    },
    {
      "kind": "text",
      "reference": "40.2",
      "text": "]εν: οὐδὲ γάρ ς’ ὁρῶ",
      "witness_prefix": "",
      "speaker": null
    },
    {
      "kind": "text",
      "reference": "40.3",
      "text": "] ἀγανακτ[",
      "witness_prefix": "",
      "speaker": null
    },
    {
      "kind": "text",
      "reference": "40.4",
      "text": "(Λα) [ ] ἐ[κ τηλι]κούτων νῦν φόβων",
      "witness_prefix": "",
      "speaker": null
    },
    {
      "kind": "text",
      "reference": "40.5",
      "text": "τὸν ὑὸν ἐκ[λυσά]μενος.",
      "witness_prefix": "",
      "speaker": null
    },
    {
      "kind": "text",
      "reference": "45.1",
      "text": "(Κλ) ἀλλὰ μὴν πάλαι",
      "witness_prefix": "",
      "speaker": null
    },
    {
      "kind": "text",
      "reference": "45.2",
      "text": "ἡμῖν ἔδοξ[ε τοῦ]τ’· ἔχει τὴν παρθένον",
      "witness_prefix": "",
      "speaker": null
    },
    {
      "kind": "text",
      "reference": "45.3",
      "text": "ὁ Μοσχίων· [ἔλαβ]’ ἐθελοντής, οὐ βίαι.",
      "witness_prefix": "",
      "speaker": null
    },
    {
      "kind": "text",
      "reference": "45.4",
      "text": "ὠιόμεθα χαλεπανεῖν σε τοῦτο πυθόμενον.",
      "witness_prefix": "",
      "speaker": null
    },
    {
      "kind": "text",
      "reference": "45.5",
      "text": "ἀστεῖος ἀποβέβηκας· εὐτυχήκαμεν· περὶ τοῦ βοῶμεν; (Λα) πῶς λέγεις; (Κλ) ὥσπερ λέγω. (Λα) οὐ Χαιρέαι τὸ πρῶτον ἐξεδώκατε",
      "witness_prefix": "",
      "speaker": null
    },
    {
      "kind": "text",
      "reference": "45.6",
      "text": "τὴν παῖδα;",
      "witness_prefix": "",
      "speaker": null
    },
    {
      "kind": "text",
      "reference": "52",
      "text": "(Κλ) μὰ Δία.",
      "witness_prefix": "",
      "speaker": null
    },
    {
      "kind": "text",
      "reference": "52.1",
      "text": "(Λα) τί σὺ λέγεις; οὐ Χαιρέαι;",
      "witness_prefix": "",
      "speaker": null
    },
    {
      "kind": "text",
      "reference": "52.2",
      "text": "ἀλλὰ τίνι;",
      "witness_prefix": "",
      "speaker": null
    },
    {
      "kind": "text",
      "reference": "53.1",
      "text": "(Κλ) πάνυ γελοῖον· οὐκ ἀκήκοας;",
      "witness_prefix": "",
      "speaker": null
    },
    {
      "kind": "text",
      "reference": "53.2",
      "text": "τῶι σῶι νεανίσκωι.",
      "witness_prefix": "",
      "speaker": null
    },
    {
      "kind": "text",
      "reference": "54",
      "text": "(Λα) τί λέγεις;",
      "witness_prefix": "",
      "speaker": null
    },
    {
      "kind": "text",
      "reference": "54",
      "text": "(Κλ) νὴ τοὺς θεούς,",
      "witness_prefix": "",
      "speaker": null
    },
    {
      "kind": "text",
      "reference": "55",
      "text": "καὶ παιδίον γὰρ γέγονεν ἐκ τούτου.",
      "witness_prefix": "",
      "speaker": null
    },
    {
      "kind": "text",
      "reference": "55.1",
      "text": "(Λα) τί φήις;",
      "witness_prefix": "",
      "speaker": null
    },
    {
      "kind": "text",
      "reference": "55.2",
      "text": "ἐκ Μοσχίωνος; ὦ πολυτίμητοι θεοί,",
      "witness_prefix": "",
      "speaker": null
    },
    {
      "kind": "text",
      "reference": "55.3",
      "text": "ἐρρωμένου πράγματος.",
      "witness_prefix": "",
      "speaker": null
    },
    {
      "kind": "text",
      "reference": "57.1",
      "text": "(Κλ) Ἄπολλον, ν[οῦν ἔχεις;",
      "witness_prefix": "",
      "speaker": null
    },
    {
      "kind": "text",
      "reference": "57.2",
      "text": "πρωί γε ς’, ὡς ἔοικ’, ἐπήινεσα.",
      "witness_prefix": "",
      "speaker": null
    },
    {
      "kind": "text",
      "reference": "58.1",
      "text": "(Λα) οὐδὲ ἓν",
      "witness_prefix": "",
      "speaker": null
    },
    {
      "kind": "text",
      "reference": "58.2",
      "text": "ὁ Χαιρέας ἄρ’ ἠδίκηται;",
      "witness_prefix": "",
      "speaker": null
    },
    {
      "kind": "text",
      "reference": "59",
      "text": "〈Κλ〉 φίλτατος—",
      "witness_prefix": "",
      "speaker": null
    },
    {
      "kind": "text",
      "reference": "60",
      "text": "τί γὰρ ἠδίκηται; —Χαιρέας.",
      "witness_prefix": "",
      "speaker": null
    },
    {
      "kind": "text",
      "reference": "60.1",
      "text": "(Λα) οὐθέν; τί οὖν",
      "witness_prefix": "",
      "speaker": null
    },
    {
      "kind": "text",
      "reference": "60.2",
      "text": "ἐβόα πορευθεὶς δεῦρο;",
      "witness_prefix": "",
      "speaker": null
    },
    {
      "kind": "text",
      "reference": "61.1",
      "text": "(Κλ) ἴσως ἐβούλετο—",
      "witness_prefix": "",
      "speaker": null
    },
    {
      "kind": "text",
      "reference": "61.2",
      "text": "(Λα) ἐβούλετ’; ἐπ’ ἐμὲ ταῦτα συνετάξασθ’ ἄρα",
      "witness_prefix": "",
      "speaker": null
    },
    {
      "kind": "text",
      "reference": "61.3",
      "text": "ὦ Γῆ.",
      "witness_prefix": "",
      "speaker": null
    },
    {
      "kind": "text",
      "reference": "63",
      "text": "(Κλ) τί ποιεῖς;",
      "witness_prefix": "",
      "speaker": null
    },
    {
      "kind": "text",
      "reference": "63",
      "text": "(Λα) οὐθέν, ἀλλ’ ὅμως ἔα δὶς ἢ τρὶς ἀνακραγεῖν με, πρὸς τῆς Ἑστίας.",
      "witness_prefix": "",
      "speaker": null
    }
  ],
  "related_author_works": [
    {
      "eul_wid": "hps-av",
      "title": {
        "english": "Apparition",
        "ancient_greek": "Φάντασμα"
      },
      "url_slug": "menander-of-athens-apparition-hps-av",
      "links": {
        "html": "https://eulogikon.org/works/menander-athens-apparition-hps-av",
        "pdf": "https://github.com/eulogikon/ancient-greek-texts/blob/main/grc/menander-of-athens-apparition-hps-av.grc.pdf",
        "md": "https://github.com/eulogikon/ancient-greek-texts/blob/main/grc/menander-of-athens-apparition-hps-av.grc.md",
        "txt": "https://github.com/eulogikon/ancient-greek-texts/blob/main/grc/menander-of-athens-apparition-hps-av.grc.txt",
        "json": "https://github.com/eulogikon/ancient-greek-texts/blob/main/grc/menander-of-athens-apparition-hps-av.grc.json",
        "epub": "https://github.com/eulogikon/ancient-greek-texts/blob/main/works/menander-athens-apparition-hps-av.epub"
      }
    },
    {
      "eul_wid": "hps-az",
      "title": {
        "english": "Arbitration",
        "ancient_greek": "Διαιτησία"
      },
      "url_slug": "menander-of-athens-arbitration-az-hps-az",
      "links": {
        "html": "https://eulogikon.org/works/menander-athens-arbitration-hps-az",
        "pdf": "https://github.com/eulogikon/ancient-greek-texts/blob/main/grc/menander-of-athens-arbitration-az-hps-az.grc.pdf",
        "md": "https://github.com/eulogikon/ancient-greek-texts/blob/main/grc/menander-of-athens-arbitration-az-hps-az.grc.md",
        "txt": "https://github.com/eulogikon/ancient-greek-texts/blob/main/grc/menander-of-athens-arbitration-az-hps-az.grc.txt",
        "json": "https://github.com/eulogikon/ancient-greek-texts/blob/main/grc/menander-of-athens-arbitration-az-hps-az.grc.json",
        "epub": "https://github.com/eulogikon/ancient-greek-texts/blob/main/works/menander-athens-arbitration-hps-az.epub"
      }
    },
    {
      "eul_wid": "hps-ax",
      "title": {
        "english": "Carthaginian",
        "ancient_greek": "Καρχηδόνιος"
      },
      "url_slug": "menander-of-athens-carthaginian-hps-ax",
      "links": {
        "html": "https://eulogikon.org/works/menander-athens-carthaginian-hps-ax",
        "pdf": "https://github.com/eulogikon/ancient-greek-texts/blob/main/grc/menander-of-athens-carthaginian-hps-ax.grc.pdf",
        "md": "https://github.com/eulogikon/ancient-greek-texts/blob/main/grc/menander-of-athens-carthaginian-hps-ax.grc.md",
        "txt": "https://github.com/eulogikon/ancient-greek-texts/blob/main/grc/menander-of-athens-carthaginian-hps-ax.grc.txt",
        "json": "https://github.com/eulogikon/ancient-greek-texts/blob/main/grc/menander-of-athens-carthaginian-hps-ax.grc.json",
        "epub": "https://github.com/eulogikon/ancient-greek-texts/blob/main/works/menander-athens-carthaginian-hps-ax.epub"
      }
    },
    {
      "eul_wid": "hps-ba",
      "title": {
        "english": "Citharist",
        "ancient_greek": "Κιθαριστής"
      },
      "url_slug": "menander-of-athens-citharist-hps-ba",
      "links": {
        "html": "https://eulogikon.org/works/menander-athens-citharist-hps-ba",
        "pdf": "https://github.com/eulogikon/ancient-greek-texts/blob/main/grc/menander-of-athens-citharist-hps-ba.grc.pdf",
        "md": "https://github.com/eulogikon/ancient-greek-texts/blob/main/grc/menander-of-athens-citharist-hps-ba.grc.md",
        "txt": "https://github.com/eulogikon/ancient-greek-texts/blob/main/grc/menander-of-athens-citharist-hps-ba.grc.txt",
        "json": "https://github.com/eulogikon/ancient-greek-texts/blob/main/grc/menander-of-athens-citharist-hps-ba.grc.json",
        "epub": "https://github.com/eulogikon/ancient-greek-texts/blob/main/works/menander-athens-citharist-hps-ba.epub"
      }
    },
    {
      "eul_wid": "hps-af",
      "title": {
        "english": "Citharists, Fragments Known Elsewhere",
        "ancient_greek": "Ἀποσπάσματα Κιθαριστῶν"
      },
      "url_slug": "menander-of-athens-citharists-fragments-hps-af",
      "links": {
        "html": "https://eulogikon.org/works/menander-athens-citharists-fragments-hps-af",
        "pdf": "https://github.com/eulogikon/ancient-greek-texts/blob/main/grc/menander-of-athens-citharists-fragments-hps-af.grc.pdf",
        "md": "https://github.com/eulogikon/ancient-greek-texts/blob/main/grc/menander-of-athens-citharists-fragments-hps-af.grc.md",
        "txt": "https://github.com/eulogikon/ancient-greek-texts/blob/main/grc/menander-of-athens-citharists-fragments-hps-af.grc.txt",
        "json": "https://github.com/eulogikon/ancient-greek-texts/blob/main/grc/menander-of-athens-citharists-fragments-hps-af.grc.json",
        "epub": "https://github.com/eulogikon/ancient-greek-texts/blob/main/works/menander-athens-citharists-fragments-hps-af.epub"
      }
    },
    {
      "eul_wid": "hps-bp",
      "title": {
        "english": "Colax",
        "ancient_greek": "Κόλαξ"
      },
      "url_slug": "menander-of-athens-colax-hps-bp",
      "links": {
        "html": "https://eulogikon.org/works/menander-athens-colax-hps-bp",
        "pdf": "https://github.com/eulogikon/ancient-greek-texts/blob/main/grc/menander-of-athens-colax-hps-bp.grc.pdf",
        "md": "https://github.com/eulogikon/ancient-greek-texts/blob/main/grc/menander-of-athens-colax-hps-bp.grc.md",
        "txt": "https://github.com/eulogikon/ancient-greek-texts/blob/main/grc/menander-of-athens-colax-hps-bp.grc.txt",
        "json": "https://github.com/eulogikon/ancient-greek-texts/blob/main/grc/menander-of-athens-colax-hps-bp.grc.json",
        "epub": "https://github.com/eulogikon/ancient-greek-texts/blob/main/works/menander-athens-colax-hps-bp.epub"
      }
    },
    {
      "eul_wid": "hps-ak",
      "title": {
        "english": "Colax, Fragments Known Elsewhere",
        "ancient_greek": "Ἀποσπάσματα Κόλακος"
      },
      "url_slug": "menander-of-athens-colax-fragments-hps-ak",
      "links": {
        "html": "https://eulogikon.org/works/menander-athens-colax-fragments-hps-ak",
        "pdf": "https://github.com/eulogikon/ancient-greek-texts/blob/main/grc/menander-of-athens-colax-fragments-hps-ak.grc.pdf",
        "md": "https://github.com/eulogikon/ancient-greek-texts/blob/main/grc/menander-of-athens-colax-fragments-hps-ak.grc.md",
        "txt": "https://github.com/eulogikon/ancient-greek-texts/blob/main/grc/menander-of-athens-colax-fragments-hps-ak.grc.txt",
        "json": "https://github.com/eulogikon/ancient-greek-texts/blob/main/grc/menander-of-athens-colax-fragments-hps-ak.grc.json",
        "epub": "https://github.com/eulogikon/ancient-greek-texts/blob/main/works/menander-athens-colax-fragments-hps-ak.epub"
      }
    },
    {
      "eul_wid": "hps-ay",
      "title": {
        "english": "Coneazomenae",
        "ancient_greek": "Κονεαζόμεναι"
      },
      "url_slug": "menander-of-athens-coneazomenae-hps-ay",
      "links": {
        "html": "https://eulogikon.org/works/menander-athens-coneazomenae-hps-ay",
        "pdf": "https://github.com/eulogikon/ancient-greek-texts/blob/main/grc/menander-of-athens-coneazomenae-hps-ay.grc.pdf",
        "md": "https://github.com/eulogikon/ancient-greek-texts/blob/main/grc/menander-of-athens-coneazomenae-hps-ay.grc.md",
        "txt": "https://github.com/eulogikon/ancient-greek-texts/blob/main/grc/menander-of-athens-coneazomenae-hps-ay.grc.txt",
        "json": "https://github.com/eulogikon/ancient-greek-texts/blob/main/grc/menander-of-athens-coneazomenae-hps-ay.grc.json",
        "epub": "https://github.com/eulogikon/ancient-greek-texts/blob/main/works/menander-athens-coneazomenae-hps-ay.epub"
      }
    },
    {
      "eul_wid": "hps-ar",
      "title": {
        "english": "Double Deceiver",
        "ancient_greek": "Διπλοῦς Ἀπατεών"
      },
      "url_slug": "menander-of-athens-double-deceiver-ar-hps-ar",
      "links": {
        "html": "https://eulogikon.org/works/menander-athens-double-deceiver-hps-ar",
        "pdf": "https://github.com/eulogikon/ancient-greek-texts/blob/main/grc/menander-of-athens-double-deceiver-ar-hps-ar.grc.pdf",
        "md": "https://github.com/eulogikon/ancient-greek-texts/blob/main/grc/menander-of-athens-double-deceiver-ar-hps-ar.grc.md",
        "txt": "https://github.com/eulogikon/ancient-greek-texts/blob/main/grc/menander-of-athens-double-deceiver-ar-hps-ar.grc.txt",
        "json": "https://github.com/eulogikon/ancient-greek-texts/blob/main/grc/menander-of-athens-double-deceiver-ar-hps-ar.grc.json",
        "epub": "https://github.com/eulogikon/ancient-greek-texts/blob/main/works/menander-athens-double-deceiver-hps-ar.epub"
      }
    },
    {
      "eul_wid": "hps-as",
      "title": {
        "english": "Doubtful Fragment",
        "ancient_greek": "Ἀμφίβολον Ἀπόσπασμα"
      },
      "url_slug": "menander-of-athens-doubtful-fragment-hps-as",
      "links": {
        "html": "https://eulogikon.org/works/menander-athens-doubtful-fragment-hps-as",
        "pdf": "https://github.com/eulogikon/ancient-greek-texts/blob/main/grc/menander-of-athens-doubtful-fragment-hps-as.grc.pdf",
        "md": "https://github.com/eulogikon/ancient-greek-texts/blob/main/grc/menander-of-athens-doubtful-fragment-hps-as.grc.md",
        "txt": "https://github.com/eulogikon/ancient-greek-texts/blob/main/grc/menander-of-athens-doubtful-fragment-hps-as.grc.txt",
        "json": "https://github.com/eulogikon/ancient-greek-texts/blob/main/grc/menander-of-athens-doubtful-fragment-hps-as.grc.json",
        "epub": "https://github.com/eulogikon/ancient-greek-texts/blob/main/works/menander-athens-doubtful-fragment-hps-as.epub"
      }
    },
    {
      "eul_wid": "hps-am",
      "title": {
        "english": "Dubious Theophorumenae Fragment",
        "ancient_greek": "Ἀμφίβολον Ἀπόσπασμα Θεοφορουμένης"
      },
      "url_slug": "menander-of-athens-theophorumenae-hps-am",
      "links": {
        "html": "https://eulogikon.org/works/menander-athens-theophorumenae-hps-am",
        "pdf": "https://github.com/eulogikon/ancient-greek-texts/blob/main/grc/menander-of-athens-theophorumenae-hps-am.grc.pdf",
        "md": "https://github.com/eulogikon/ancient-greek-texts/blob/main/grc/menander-of-athens-theophorumenae-hps-am.grc.md",
        "txt": "https://github.com/eulogikon/ancient-greek-texts/blob/main/grc/menander-of-athens-theophorumenae-hps-am.grc.txt",
        "json": "https://github.com/eulogikon/ancient-greek-texts/blob/main/grc/menander-of-athens-theophorumenae-hps-am.grc.json",
        "epub": "https://github.com/eulogikon/ancient-greek-texts/blob/main/works/menander-athens-theophorumenae-hps-am.epub"
      }
    },
    {
      "eul_wid": "hps-bm",
      "title": {
        "english": "Dyscolus",
        "ancient_greek": "Δύσκολος"
      },
      "url_slug": "menander-of-athens-dyscolus-hps-bm",
      "links": {
        "html": "https://eulogikon.org/works/menander-athens-dyscolus-hps-bm",
        "pdf": "https://github.com/eulogikon/ancient-greek-texts/blob/main/grc/menander-of-athens-dyscolus-hps-bm.grc.pdf",
        "md": "https://github.com/eulogikon/ancient-greek-texts/blob/main/grc/menander-of-athens-dyscolus-hps-bm.grc.md",
        "txt": "https://github.com/eulogikon/ancient-greek-texts/blob/main/grc/menander-of-athens-dyscolus-hps-bm.grc.txt",
        "json": "https://github.com/eulogikon/ancient-greek-texts/blob/main/grc/menander-of-athens-dyscolus-hps-bm.grc.json",
        "epub": "https://github.com/eulogikon/ancient-greek-texts/blob/main/works/menander-athens-dyscolus-hps-bm.epub"
      }
    }
  ],
  "related_domain_works": [
    {
      "eul_wid": "kfu-ac",
      "title": {
        "english": "Anonymous New Comedies",
        "ancient_greek": "Ἀνώνυμοι Νέαι Κωμῳδίαι"
      },
      "url_slug": "comic-fragments-anonymous-ii-new-comedies-kfu-ac",
      "links": {
        "html": "https://eulogikon.org/works/anon-comic-fragments-ii-new-comedies-kfu-ac",
        "pdf": "https://github.com/eulogikon/ancient-greek-texts/blob/main/grc/comic-fragments-anonymous-ii-new-comedies-kfu-ac.grc.pdf",
        "md": "https://github.com/eulogikon/ancient-greek-texts/blob/main/grc/comic-fragments-anonymous-ii-new-comedies-kfu-ac.grc.md",
        "txt": "https://github.com/eulogikon/ancient-greek-texts/blob/main/grc/comic-fragments-anonymous-ii-new-comedies-kfu-ac.grc.txt",
        "json": "https://github.com/eulogikon/ancient-greek-texts/blob/main/grc/comic-fragments-anonymous-ii-new-comedies-kfu-ac.grc.json",
        "epub": "https://github.com/eulogikon/ancient-greek-texts/blob/main/works/anon-comic-fragments-ii-new-comedies-kfu-ac.epub"
      }
    },
    {
      "eul_wid": "fim-ab",
      "title": {
        "english": "Comic Fragments on Daily Life",
        "ancient_greek": "Ἀποσπάσματα περὶ Βίου Καθημερινοῦ Κωμικά"
      },
      "url_slug": "alcaeus-the-comic-poet-daily-life-ab-fim-ab",
      "links": {
        "html": "https://eulogikon.org/works/alcaeus-comic-daily-life-fim-ab",
        "pdf": "https://github.com/eulogikon/ancient-greek-texts/blob/main/grc/alcaeus-the-comic-poet-daily-life-ab-fim-ab.grc.pdf",
        "md": "https://github.com/eulogikon/ancient-greek-texts/blob/main/grc/alcaeus-the-comic-poet-daily-life-ab-fim-ab.grc.md",
        "txt": "https://github.com/eulogikon/ancient-greek-texts/blob/main/grc/alcaeus-the-comic-poet-daily-life-ab-fim-ab.grc.txt",
        "json": "https://github.com/eulogikon/ancient-greek-texts/blob/main/grc/alcaeus-the-comic-poet-daily-life-ab-fim-ab.grc.json",
        "epub": "https://github.com/eulogikon/ancient-greek-texts/blob/main/works/alcaeus-comic-daily-life-fim-ab.epub"
      }
    },
    {
      "eul_wid": "cwq-aa",
      "title": {
        "english": "Comic Fragments on Food and Feasting",
        "ancient_greek": "Ἀποσπάσματα περὶ Τροφῆς καὶ Εὐωχίας"
      },
      "url_slug": "epilycus-the-comic-poet-comic-food-feasting-cwq-aa",
      "links": {
        "html": "https://eulogikon.org/works/epilycus-comic-food-feasting-cwq-aa",
        "pdf": "https://github.com/eulogikon/ancient-greek-texts/blob/main/grc/epilycus-the-comic-poet-comic-food-feasting-cwq-aa.grc.pdf",
        "md": "https://github.com/eulogikon/ancient-greek-texts/blob/main/grc/epilycus-the-comic-poet-comic-food-feasting-cwq-aa.grc.md",
        "txt": "https://github.com/eulogikon/ancient-greek-texts/blob/main/grc/epilycus-the-comic-poet-comic-food-feasting-cwq-aa.grc.txt",
        "json": "https://github.com/eulogikon/ancient-greek-texts/blob/main/grc/epilycus-the-comic-poet-comic-food-feasting-cwq-aa.grc.json",
        "epub": "https://github.com/eulogikon/ancient-greek-texts/blob/main/works/epilycus-comic-food-feasting-cwq-aa.epub"
      }
    },
    {
      "eul_wid": "kfu-ai",
      "title": {
        "english": "Doubts",
        "ancient_greek": "Ἀμφιβολίαι"
      },
      "url_slug": "comic-fragments-anonymous-ii-doubts-kfu-ai",
      "links": {
        "html": "https://eulogikon.org/works/anon-comic-fragments-ii-doubts-kfu-ai",
        "pdf": "https://github.com/eulogikon/ancient-greek-texts/blob/main/grc/comic-fragments-anonymous-ii-doubts-kfu-ai.grc.pdf",
        "md": "https://github.com/eulogikon/ancient-greek-texts/blob/main/grc/comic-fragments-anonymous-ii-doubts-kfu-ai.grc.md",
        "txt": "https://github.com/eulogikon/ancient-greek-texts/blob/main/grc/comic-fragments-anonymous-ii-doubts-kfu-ai.grc.txt",
        "json": "https://github.com/eulogikon/ancient-greek-texts/blob/main/grc/comic-fragments-anonymous-ii-doubts-kfu-ai.grc.json",
        "epub": "https://github.com/eulogikon/ancient-greek-texts/blob/main/works/anon-comic-fragments-ii-doubts-kfu-ai.epub"
      }
    },
    {
      "eul_wid": "dum-ad",
      "title": {
        "english": "Fragments on Athenian Politicians",
        "ancient_greek": "Ἀποσπάσματα περὶ τῶν Ἀθηναίων Πολιτικῶν"
      },
      "url_slug": "eupolis-of-athens-politicians-dum-ad",
      "links": {
        "html": "https://eulogikon.org/works/eupolis-athens-politicians-dum-ad",
        "pdf": "https://github.com/eulogikon/ancient-greek-texts/blob/main/grc/eupolis-of-athens-politicians-dum-ad.grc.pdf",
        "md": "https://github.com/eulogikon/ancient-greek-texts/blob/main/grc/eupolis-of-athens-politicians-dum-ad.grc.md",
        "txt": "https://github.com/eulogikon/ancient-greek-texts/blob/main/grc/eupolis-of-athens-politicians-dum-ad.grc.txt",
        "json": "https://github.com/eulogikon/ancient-greek-texts/blob/main/grc/eupolis-of-athens-politicians-dum-ad.grc.json",
        "epub": "https://github.com/eulogikon/ancient-greek-texts/blob/main/works/eupolis-athens-politicians-dum-ad.epub"
      }
    },
    {
      "eul_wid": "eec-ab",
      "title": {
        "english": "Fragments on Comedy",
        "ancient_greek": "Ἀποσπάσματα περὶ Κωμῳδίας"
      },
      "url_slug": "cephisodorus-the-comic-poet-fragments-eec-ab",
      "links": {
        "html": "https://eulogikon.org/works/cephisodorus-comic-fragments-eec-ab",
        "pdf": "https://github.com/eulogikon/ancient-greek-texts/blob/main/grc/cephisodorus-the-comic-poet-fragments-eec-ab.grc.pdf",
        "md": "https://github.com/eulogikon/ancient-greek-texts/blob/main/grc/cephisodorus-the-comic-poet-fragments-eec-ab.grc.md",
        "txt": "https://github.com/eulogikon/ancient-greek-texts/blob/main/grc/cephisodorus-the-comic-poet-fragments-eec-ab.grc.txt",
        "json": "https://github.com/eulogikon/ancient-greek-texts/blob/main/grc/cephisodorus-the-comic-poet-fragments-eec-ab.grc.json",
        "epub": "https://github.com/eulogikon/ancient-greek-texts/blob/main/works/cephisodorus-comic-fragments-eec-ab.epub"
      }
    },
    {
      "eul_wid": "iie-aa",
      "title": {
        "english": "Fragments on Life and Fortune",
        "ancient_greek": "Ἀποσπάσματα περὶ Βίου καὶ Τύχης"
      },
      "url_slug": "apollodorus-of-carystus-i-life-fortune-iie-aa",
      "links": {
        "html": "https://eulogikon.org/works/apollodorus-carystus-life-fortune-iie-aa",
        "pdf": "https://github.com/eulogikon/ancient-greek-texts/blob/main/grc/apollodorus-of-carystus-i-life-fortune-iie-aa.grc.pdf",
        "md": "https://github.com/eulogikon/ancient-greek-texts/blob/main/grc/apollodorus-of-carystus-i-life-fortune-iie-aa.grc.md",
        "txt": "https://github.com/eulogikon/ancient-greek-texts/blob/main/grc/apollodorus-of-carystus-i-life-fortune-iie-aa.grc.txt",
        "json": "https://github.com/eulogikon/ancient-greek-texts/blob/main/grc/apollodorus-of-carystus-i-life-fortune-iie-aa.grc.json",
        "epub": "https://github.com/eulogikon/ancient-greek-texts/blob/main/works/apollodorus-carystus-life-fortune-iie-aa.epub"
      }
    },
    {
      "eul_wid": "cgm-aa",
      "title": {
        "english": "Fragments on a Banquet",
        "ancient_greek": "Ἀποσπάσματα περὶ Συμποσίου"
      },
      "url_slug": "timotheus-the-comic-poet-of-athens-banquet-fragments-cgm-aa",
      "links": {
        "html": "https://eulogikon.org/works/timotheus-athens-banquet-fragments-cgm-aa",
        "pdf": "https://github.com/eulogikon/ancient-greek-texts/blob/main/grc/timotheus-the-comic-poet-of-athens-banquet-fragments-cgm-aa.grc.pdf",
        "md": "https://github.com/eulogikon/ancient-greek-texts/blob/main/grc/timotheus-the-comic-poet-of-athens-banquet-fragments-cgm-aa.grc.md",
        "txt": "https://github.com/eulogikon/ancient-greek-texts/blob/main/grc/timotheus-the-comic-poet-of-athens-banquet-fragments-cgm-aa.grc.txt",
        "json": "https://github.com/eulogikon/ancient-greek-texts/blob/main/grc/timotheus-the-comic-poet-of-athens-banquet-fragments-cgm-aa.grc.json",
        "epub": "https://github.com/eulogikon/ancient-greek-texts/blob/main/works/timotheus-athens-banquet-fragments-cgm-aa.epub"
      }
    }
  ],
  "links": {
    "html": "https://eulogikon.org/works/menander-athens-uncertain-fable-hps-au",
    "pdf": "https://github.com/eulogikon/ancient-greek-texts/blob/main/grc/menander-of-athens-uncertain-fable-hps-au.grc.pdf",
    "md": "https://github.com/eulogikon/ancient-greek-texts/blob/main/grc/menander-of-athens-uncertain-fable-hps-au.grc.md",
    "txt": "https://github.com/eulogikon/ancient-greek-texts/blob/main/grc/menander-of-athens-uncertain-fable-hps-au.grc.txt",
    "json": "https://github.com/eulogikon/ancient-greek-texts/blob/main/grc/menander-of-athens-uncertain-fable-hps-au.grc.json",
    "epub": "https://github.com/eulogikon/ancient-greek-texts/blob/main/works/menander-athens-uncertain-fable-hps-au.epub"
  },
  "license": "https://creativecommons.org/publicdomain/mark/1.0/"
}
